backdoor_ww/__init__.py
backdoor_ww/backdoor.txt
backdoor_ww/script.py
backdoor_ww-0.1.2.dist-info/LICENSE
backdoor_ww-0.1.2.dist-info/METADATA
backdoor_ww-0.1.2.dist-info/WHEEL
backdoor_ww-0.1.2.dist-info/top_level.txt
backdoor_ww-0.1.2.dist-info/RECORD
