Metadata-Version: 2.1
Name: backdoor-ww
Version: 0.1.2
Summary: Backdoor attack by PyPI package
License-File: LICENSE
